snscrape/__init__.py
snscrape/_cli.py
snscrape/base.py
snscrape/version.py
snscrape/modules/__init__.py
snscrape/modules/facebook.py
snscrape/modules/instagram.py
snscrape/modules/mastodon.py
snscrape/modules/reddit.py
snscrape/modules/telegram.py
snscrape/modules/twitter.py
snscrape/modules/vkontakte.py
snscrape/modules/weibo.py
snscrape_cyberconnect-0.0.1.dist-info/LICENSE
snscrape_cyberconnect-0.0.1.dist-info/METADATA
snscrape_cyberconnect-0.0.1.dist-info/WHEEL
snscrape_cyberconnect-0.0.1.dist-info/entry_points.txt
snscrape_cyberconnect-0.0.1.dist-info/top_level.txt
snscrape_cyberconnect-0.0.1.dist-info/RECORD
