Metadata-Version: 2.1
Name: snscrape-cyberconnect
Version: 0.0.1
Summary: A social networking service scraper
Home-page: https://github.com/nazihkalo/snscrape-cyberconnect
Author: Nazih Kalo
Classifier: Development Status :: 4 - Beta
Classifier: License :: OSI Approved :: GNU General Public License v3 or later (GPLv3+)
Classifier: Programming Language :: Python :: 3.8
Classifier: Programming Language :: Python :: 3.9
Classifier: Programming Language :: Python :: 3.10
Requires-Python: ~=3.9
License-File: LICENSE
Requires-Dist: requests[socks]
Requires-Dist: lxml
Requires-Dist: beautifulsoup4
Requires-Dist: filelock
Requires-Dist: pytz ; python_version < "3.9.0"
Provides-Extra: test
Requires-Dist: coverage ; extra == 'test'
